Metadata-Version: 1.0
Name: crabapple
Version: 0.1.0
Summary: Json algorithm based on groupby
Home-page: https://github.com/soukon9/crabapple
Author: crabapple
Author-email: 417993072@qq.com
License: MIT Licence
Keywords: pip,crabapple,Crabapple,CrabappleJson
Platform: any
